Workbook

Sheet Cover
B2: Corewell Health – Snowflake Data Due-Diligence & Assessment (DD&A)
B3: Architecture Health Check, Gap Analysis, and Roadmap
B5: Version | C5: v2.0
B6: Prepared By | C6: Pradipta
B7: Client | C7: Corewell Health
B8: Scope | C8: Snowflake platform + surrounding data ecosystem (IBM DW, MS SQL, Mongo, Tableau/PowerBI/SAS, Azure AD)
B9: Deliverables | C9: Executive Summary, Maturity Scorecard, Gap Analysis, FinOps Recs, 30/60/90 Roadmap
B12: How to use this workbook
B13: 1. Each tab represents one assessment domain (22 in total).
B14: 2. Common columns: Category, Assessment Question, Current State, Evidence, Risk, Recommendation, Priority, Best Practice, Maturity (1-5), Owner, Target Date.
B15: 3. Score each question on Maturity 1-5 using the 'Maturity Model' tab.
B16: 4. Domain scores roll up to the 'Executive Summary' tab.
B17: 5. Attach evidence (screenshot / query / doc link) in the Evidence column.
B18: 6. Use Risk = H/M/L and Priority = H/M/L for the remediation roadmap.

Sheet Agenda
A1: Assessment Agenda
A3: Sno | B3: Section | C3: Owner | D3: Status | E3: % Complete | F3: Notes
A4: 1 | B4: Organization & Governance | D4: Not Started
A5: 2 | B5: Snowflake Account Architecture | D5: Not Started
A6: 3 | B6: Security & Identity | D6: Not Started
A7: 4 | B7: Networking | D7: Not Started
A8: 5 | B8: Data Architecture | D8: Not Started
A9: 6 | B9: Data Ingestion | D9: Not Started
A10: 7 | B10: Data Transformation | D10: Not Started
A11: 8 | B11: Data Modeling | D11: Not Started
A12: 9 | B12: Compute & Warehouses | D12: Not Started
A13: 10 | B13: Storage & Data Lifecycle | D13: Not Started
A14: 11 | B14: Performance Optimization | D14: Not Started
A15: 12 | B15: Cost Optimization (FinOps) | D15: Not Started
... A25: 22 | B25: Roadmap & Recommendations | D25: Not Started

Sheet Maturity Model
A1: Maturity Scoring Model
A3: Score | B3: Level | C3: Description | D3: What it looks like
A4: 1 | B4: Initial / Ad Hoc | C4: No formal process; reactive. | D4: No standards, no documentation, tribal knowledge only.
A5: 2 | B5: Basic | C5: Some processes exist but inconsistent. | D5: Partial coverage, manual, some documentation.
A6: 3 | B6: Defined | C6: Standards documented and followed. | D6: Playbooks exist, roles defined, repeatable outcomes.
A7: 4 | B7: Managed | C7: Measured, monitored, automated. | D7: KPIs tracked, automation in place, proactive alerting.
A8: 5 | B8: Optimized / Best | C8: Continuously improved; industry-leading. | D8: FinOps, DevOps, DataOps mature; AI/automation drives improvement.

Sheet 1_Governance
A1: 1. Organization & Governance
A2: Corewell Snowflake DD&A – capture Current State, Evidence, and Recommendation for each question. Score Maturity 1-5.
A4: Sno | B4: Category | C4: Assessment Question | D4: Current State | E4: Evidence | F4: Risk (H/M/L) | G4: Recommendation | H4: Priority (H/M/L) | I4: Best Practice | J4: Maturity (1-5) | K4: Owner | L4: Target Date
A5: 1 | B5: Business Drivers | C5: Why did Corewell choose Snowflake? What business problem drove adoption?
A6: 2 | B6: Business Drivers | C6: What are the top 3 business outcomes expected from the Snowflake platform?
A7: 3 | B7: Business Drivers | C7: How many business domains / lines of business consume the platform today?
A8: 4 | B8: Business Drivers | C8: Is there an enterprise data strategy document? When was it last updated?
A9: 5 | B9: Business Drivers | C9: How is Snowflake positioned vs the legacy IBM DW – full replacement, coexistence, or offload?
A10: 6 | B10: Business Drivers | C10: What is the executive sponsorship model for the data platform?
A11: 7 | B11: Operating Model | C11: Who owns the Snowflake platform (Central Data Platform team vs federated)?
A12: 8 | B12: Operating Model | C12: Is there a Center of Excellence (CoE) for Snowflake / cloud data?
A13: 9 | B13: Operating Model | C13: Are platform, data engineering, analytics, and governance responsibilities clearly split (RACI)?
A14: 10 | B14: Operating Model | C14: How are new use cases intake, prioritized, and funded (chargeback / showback)?
A15: 11 | B15: Data Governance | C15: Is there a formal Data Governance Council / Committee?
A16: 12 | B16: Data Governance | C16: Are Data Owners and Data Stewards assigned per domain?
... A23: 19 | B23: Data Governance | C23: Is there a formal data contract / SLA between producers and consumers?

Sheet 2_AccountArch
A1: 2. Snowflake Account Architecture
A2: Corewell Snowflake DD&A – capture Current State, Evidence, and Recommendation for each question. Score Maturity 1-5.
A4: Sno | B4: Category | C4: Assessment Question | D4: Current State | E4: Evidence | F4: Risk (H/M/L) | G4: Recommendation | H4: Priority (H/M/L) | I4: Best Practice | J4: Maturity (1-5) | K4: Owner | L4: Target Date
A5: 1 | B5: Account Topology | C5: How many Snowflake accounts exist (Dev / Test / Prod / Sandbox / DR)?
A6: 2 | B6: Account Topology | C6: Is the Organization (ORGADMIN) feature enabled and used for account management?
A7: 3 | B7: Account Topology | C7: Cloud provider(s) – AWS, Azure, GCP? Region(s)?
A8: 4 | B8: Account Topology | C8: Rationale for chosen region(s) – data residency, latency, HIPAA BAA coverage?
A9: 5 | B9: Account Topology | C9: Multi-cloud strategy – active or planned?
A10: 6 | B10: Account Topology | C10: Cross-region / cross-cloud replication configured (Database Replication / Failover Groups)?
A11: 7 | B11: Environment Separation | C11: Are Dev / Test / Prod strictly isolated at the account level (recommended) or database level?
A12: 8 | B12: Environment Separation | C12: Are non-prod environments refreshed from prod (masked)? How often?
A13: 9 | B13: Environment Separation | C13: Business unit / domain isolation model (accounts vs databases vs schemas)?
A14: 10 | B14: Account Governance | C14: Are Resource Monitors configured at the account and warehouse level?
A15: 11 | B15: Account Governance | C15: Are account-level parameters (STATEMENT_TIMEOUT_IN_SECONDS, DATA_RETENTION_TIME_IN_DAYS, etc.) set intentionally?
A16: 12 | B16: Account Governance | C16: ORGADMIN, ACCOUNTADMIN, SECURITYADMIN – how many humans hold each? MFA enforced?
A17: 13 | B17: Account Governance | C17: Account locator strategy documented?

Sheet 3_Security
A1: 3. Security & Identity
A2: Corewell Snowflake DD&A – capture Current State, Evidence, and Recommendation for each question. Score Maturity 1-5.
A4: Sno | B4: Category | C4: Assessment Question | D4: Current State | E4: Evidence | F4: Risk (H/M/L) | G4: Recommendation | H4: Priority (H/M/L) | I4: Best Practice | J4: Maturity (1-5) | K4: Owner | L4: Target Date
A5: 1 | B5: Identity & Authentication | C5: Is SSO enabled? Identity Provider (Azure AD / Okta / Ping)?
A6: 2 | B6: Identity & Authentication | C6: MFA – enforced for all users? For service accounts?
A7: 3 | B7: Identity & Authentication | C7: SCIM provisioning enabled for user + group lifecycle?
A8: 4 | B8: Identity & Authentication | C8: Are service accounts using key-pair auth or OAuth (not passwords)?
A9: 5 | B9: Identity & Authentication | C9: Password policy: length, complexity, rotation, lockout?
A10: 6 | B10: Identity & Authentication | C10: Legacy user accounts – any without SSO / MFA? Break-glass process documented?
A11: 7 | B11: Authorization (RBAC) | C11: RBAC model documented? Functional roles vs access roles pattern used?
A12: 8 | B12: Authorization (RBAC) | C12: Role hierarchy diagrammed and maintained?
A13: 9 | B13: Authorization (RBAC) | C13: Least-privilege enforced – no direct grants to users, only via roles?
A14: 10 | B14: Authorization (RBAC) | C14: Future grants configured for new objects?
A15: 11 | B15: Authorization (RBAC) | C15: Are ACCOUNTADMIN / SECURITYADMIN used only for privileged tasks?
A16: 12 | B16: Authorization (RBAC) | C16: Are custom admin roles used instead of built-in for daily ops?
... A26: 22 | B26: Secrets & Integrations | C26: Are external integrations (S3, Blob, GCS, Kafka) using Storage Integrations (not embedded creds)?

Sheet 4_Networking
A1: 4. Networking
A2: Corewell Snowflake DD&A – capture Current State, Evidence, and Recommendation for each question. Score Maturity 1-5.
A4: Sno | B4: Category | C4: Assessment Question | D4: Current State | E4: Evidence | F4: Risk (H/M/L) | G4: Recommendation | H4: Priority (H/M/L) | I4: Best Practice | J4: Maturity (1-5) | K4: Owner | L4: Target Date
A5: 1 | B5: Private Connectivity | C5: Is Snowflake accessed over the public internet or PrivateLink / Private Endpoint?
A6: 2 | B6: Private Connectivity | C6: AWS PrivateLink / Azure Private Link / GCP Private Service Connect configured?
A7: 3 | B7: Private Connectivity | C7: Is Snowsight / OCSP traffic also on private connectivity?
A8: 4 | B8: Network Policies | C8: Account-level and user-level Network Policies configured?
A9: 5 | B9: Network Policies | C9: IP allow-lists reviewed and pruned regularly?
A10: 6 | B10: Network Policies | C10: Are BI tools, ETL tools, and admin workstations traffic-restricted appropriately?
A11: 7 | B11: Enterprise Connectivity | C11: VPN / ExpressRoute / Direct Connect used for on-prem to Snowflake?
A12: 8 | B12: Enterprise Connectivity | C12: VPC / VNet Peering to source systems where required?
A13: 9 | B13: Enterprise Connectivity | C13: Egress controls to prevent data exfiltration to unapproved regions/accounts?

Sheet 5_DataArch
A1: 5. Data Architecture
A2: Corewell Snowflake DD&A – capture Current State, Evidence, and Recommendation for each question. Score Maturity 1-5.
A4: Sno | B4: Category | C4: Assessment Question | D4: Current State | E4: Evidence | F4: Risk (H/M/L) | G4: Recommendation | H4: Priority (H/M/L) | I4: Best Practice | J4: Maturity (1-5) | K4: Owner | L4: Target Date
A5: 1 | B5: Landscape | C5: How many databases, schemas exist today? Growth trend?
A6: 2 | B6: Landscape | C6: Data domains mapped to databases/schemas – documented?
A7: 3 | B7: Landscape | C7: Which architecture pattern is followed – Medallion (Bronze/Silver/Gold), Data Vault, Kimball star, Data Mesh, Lakehouse?
A8: 4 | B8: Landscape | C8: Is there a reference architecture diagram? Last updated when?
A9: 5 | B9: Legacy Coexistence | C9: How is data flowing from IBM DB2 / IBM IaaS DW into Snowflake today?
A10: 6 | B10: Legacy Coexistence | C10: Migration wave plan from IBM DW to Snowflake – documented?
A11: 7 | B11: Legacy Coexistence | C11: MS SQL Server – source of truth or being retired? Sync pattern?
A12: 8 | B12: Legacy Coexistence | C12: MongoDB – how are semi-structured docs landed (VARIANT / Iceberg)?
A13: 9 | B13: Advanced Patterns | C13: Is CDC used for source ingestion? Which tool (Fivetran / Qlik / Debezium / native)?
A14: 10 | B14: Advanced Patterns | C14: Time Travel retention set per data class?
A15: 11 | B15: Advanced Patterns | C15: Fail-safe understood and factored into storage costs?
A16: 12 | B16: Advanced Patterns | C16: Zero-copy Clones used for dev/test/QA?
... A18: 14 | B18: Advanced Patterns | C18: External Tables / Hybrid Tables used?

Sheet 6_Ingestion
A1: 6. Data Ingestion
A2: Corewell Snowflake DD&A – capture Current State, Evidence, and Recommendation for each question. Score Maturity 1-5.
A4: Sno | B4: Category | C4: Assessment Question | D4: Current State | E4: Evidence | F4: Risk (H/M/L) | G4: Recommendation | H4: Priority (H/M/L) | I4: Best Practice | J4: Maturity (1-5) | K4: Owner | L4: Target Date
A5: 1 | B5: Sources | C5: Inventory of source systems (Oracle, SQL Server, DB2, SAP, Epic/Cerner EHR, Salesforce, Kafka, S3, Blob, GCS, APIs, flat files)?
A6: 2 | B6: Sources | C6: Volume per source (rows/day, GB/day)?
A7: 3 | B7: Sources | C7: Frequency – batch, micro-batch, streaming?
A8: 4 | B8: Ingestion Patterns | C8: Snowpipe (auto-ingest) used for continuous file loads?
A9: 5 | B9: Ingestion Patterns | C9: Snowpipe Streaming / Kafka Connector for real-time?
A10: 6 | B10: Ingestion Patterns | C10: Fivetran / Matillion / Informatica / ADF / Glue / dbt – which and for what?
A11: 7 | B11: Ingestion Patterns | C11: Are ingestion pipelines idempotent and re-runnable?
A12: 8 | B12: Ingestion Patterns | C12: Watermark / high-water-mark strategy for incremental loads?
A13: 9 | B13: Reliability & Quality at Ingest | C13: Retry logic and Dead Letter Queue for failed records?
A14: 10 | B14: Reliability & Quality at Ingest | C14: Duplicate detection at ingest?
A15: 11 | B15: Reliability & Quality at Ingest | C15: Late-arriving data handling documented?
A16: 12 | B16: Reliability & Quality at Ingest | C16: Schema drift handled automatically or manually?
... A19: 15 | B19: SFTP / Flat Files | C19: Are PGP / encryption controls applied for files with PHI?

Sheet 7_Transform
A1: 7. Data Transformation
A2: Corewell Snowflake DD&A – capture Current State, Evidence, and Recommendation for each question. Score Maturity 1-5.
A4: Sno | B4: Category | C4: Assessment Question | D4: Current State | E4: Evidence | F4: Risk (H/M/L) | G4: Recommendation | H4: Priority (H/M/L) | I4: Best Practice | J4: Maturity (1-5) | K4: Owner | L4: Target Date
A5: 1 | B5: Tooling | C5: Primary transformation tool – dbt, Snowpark, Stored Procedures, Informatica, Matillion?
A6: 2 | B6: Tooling | C6: ELT (recommended) or ETL pattern?
A7: 3 | B7: Tooling | C7: Python / Java / Scala / Spark – where and why?
A8: 4 | B8: Tooling | C8: Is Snowpark being adopted? For which use cases?
A9: 5 | B9: Engineering Practices | C9: Are transformations modular and version-controlled?
A10: 6 | B10: Engineering Practices | C10: Incremental models used where possible?
A11: 7 | B11: Engineering Practices | C11: Dependency management (dbt DAG / Airflow / Snowflake Tasks)?
A12: 8 | B12: Engineering Practices | C12: Unit tests / data tests (dbt tests, Great Expectations) in place?
A13: 9 | B13: Engineering Practices | C13: Error handling & alerting on failures?
A14: 10 | B14: Engineering Practices | C14: How are business logic changes governed (peer review, approvals)?
A15: 11 | B15: Orchestration | C15: Primary orchestrator – Airflow, ADF, Snowflake Tasks, dbt Cloud, Prefect?
A16: 12 | B16: Orchestration | C16: SLA-driven scheduling? Dependencies across pipelines managed?

Sheet 8_Modeling
A1: 8. Data Modeling
A2: Corewell Snowflake DD&A – capture Current State, Evidence, and Recommendation for each question. Score Maturity 1-5.
A4: Sno | B4: Category | C4: Assessment Question | D4: Current State | E4: Evidence | F4: Risk (H/M/L) | G4: Recommendation | H4: Priority (H/M/L) | I4: Best Practice | J4: Maturity (1-5) | K4: Owner | L4: Target Date
A5: 1 | B5: Approach | C5: Modeling approach – Kimball star, Snowflake schema, Data Vault 2.0, 3NF, Wide table / OBT?
A6: 2 | B6: Approach | C6: Consistent modeling standards across domains?
A7: 3 | B7: Approach | C7: Conformed dimensions defined and reused?
A8: 4 | B8: Techniques | C8: Slowly Changing Dimensions – which types (1/2/3/6) and where?
A9: 5 | B9: Techniques | C9: Fact table grain documented per fact?
A10: 6 | B10: Techniques | C10: Materialized Views used – where and why?
A11: 7 | B11: Techniques | C11: Dynamic Tables in use? Refresh lag configured?
A12: 8 | B12: Techniques | C12: Views vs Tables strategy for consumption layer?
A13: 9 | B13: Semantic Layer | C13: Is there a semantic layer (dbt semantic layer / Cube / AtScale / BI-native)?
A14: 10 | B14: Semantic Layer | C14: Metric definitions centralized to avoid duplication in Tableau / PowerBI / SAS?

Sheet 9_Compute
A1: 9. Compute & Warehouses
A2: Corewell Snowflake DD&A – capture Current State, Evidence, and Recommendation for each question. Score Maturity 1-5.
A4: Sno | B4: Category | C4: Assessment Question | D4: Current State | E4: Evidence | F4: Risk (H/M/L) | G4: Recommendation | H4: Priority (H/M/L) | I4: Best Practice | J4: Maturity (1-5) | K4: Owner | L4: Target Date
A5: 1 | B5: Warehouse Design | C5: How many warehouses exist? Naming and purpose documented?
A6: 2 | B6: Warehouse Design | C6: Right-sizing – XS/S/M/L/XL/... – how were sizes chosen?
A7: 3 | B7: Warehouse Design | C7: Auto-Suspend timeout per warehouse? (Best practice: 60s for interactive, higher for pipelines.)
A8: 4 | B8: Warehouse Design | C8: Auto-Resume enabled?
A9: 5 | B9: Warehouse Design | C9: Multi-Cluster warehouses used for concurrency? Min/Max cluster settings?
A10: 6 | B10: Warehouse Design | C10: Scaling Policy – Standard or Economy?
A11: 7 | B11: Warehouse Design | C11: Query Acceleration Service enabled where appropriate?
A12: 8 | B12: Warehouse Design | C12: Snowpark-Optimized warehouses used for Snowpark/ML workloads?
A13: 9 | B13: Workload Isolation | C13: Dedicated warehouses per workload class (ETL / BI / ad-hoc / data science)?
A14: 10 | B14: Workload Isolation | C14: Any noisy-neighbor / queueing issues observed?
A15: 11 | B15: Workload Isolation | C15: Warehouse utilization tracked (WAREHOUSE_LOAD_HISTORY)?

Sheet 10_Storage
A1: 10. Storage & Data Lifecycle
A2: Corewell Snowflake DD&A – capture Current State, Evidence, and Recommendation for each question. Score Maturity 1-5.
A4: Sno | B4: Category | C4: Assessment Question | D4: Current State | E4: Evidence | F4: Risk (H/M/L) | G4: Recommendation | H4: Priority (H/M/L) | I4: Best Practice | J4: Maturity (1-5) | K4: Owner | L4: Target Date
A5: 1 | B5: Volume & Growth | C5: Current storage size (TB) and monthly growth rate?
A6: 2 | B6: Volume & Growth | C6: Top 10 largest tables and their growth?
A7: 3 | B7: Volume & Growth | C7: Compression ratio per major table?
A8: 4 | B8: Retention | C8: Time Travel retention configured per table/schema (0-90 days)?
A9: 5 | B9: Retention | C9: Fail-safe cost understood; large tables reviewed for necessity?
A10: 6 | B10: Retention | C10: Transient / Temporary tables used where Fail-safe not needed?
A11: 7 | B11: Lifecycle | C11: Data archival / purge policy in place?
A12: 8 | B12: Lifecycle | C12: Cold data offloaded to Iceberg / external stages?
A13: 9 | B13: Lifecycle | C13: Zero-copy Clone lifecycle – old clones cleaned up?

Sheet 11_Performance
A1: 11. Performance Optimization
A2: Corewell Snowflake DD&A – capture Current State, Evidence, and Recommendation for each question. Score Maturity 1-5.
A4: Sno | B4: Category | C4: Assessment Question | D4: Current State | E4: Evidence | F4: Risk (H/M/L) | G4: Recommendation | H4: Priority (H/M/L) | I4: Best Practice | J4: Maturity (1-5) | K4: Owner | L4: Target Date
A5: 1 | B5: Query Performance | C5: Average / p95 query runtime by workload?
A6: 2 | B6: Query Performance | C6: Top 20 slowest / most expensive queries reviewed weekly?
A7: 3 | B7: Query Performance | C7: Queue time (WAREHOUSE_LOAD_HISTORY) acceptable?
A8: 4 | B8: Optimization Features | C8: Clustering keys defined on large tables? Reclustering cost monitored?
A9: 5 | B9: Optimization Features | C9: Search Optimization Service enabled for point-lookup tables?
A10: 6 | B10: Optimization Features | C10: Materialized Views used appropriately?
A11: 7 | B11: Optimization Features | C11: Result cache / metadata cache hit rate tracked?
A12: 8 | B12: Optimization Features | C12: Micro-partition pruning validated via QUERY_HISTORY / EXPLAIN?
A13: 9 | B13: Design Anti-Patterns | C13: SELECT * usage in production queries?
A14: 10 | B14: Design Anti-Patterns | C14: Cross-joins, cartesian products, non-SARGable predicates identified?
A15: 11 | B15: Design Anti-Patterns | C15: Excessive small-file loads (Snowpipe file size)?

Sheet 12_FinOps
A1: 12. Cost Optimization (FinOps)
A2: Corewell Snowflake DD&A – capture Current State, Evidence, and Recommendation for each question. Score Maturity 1-5.
A4: Sno | B4: Category | C4: Assessment Question | D4: Current State | E4: Evidence | F4: Risk (H/M/L) | G4: Recommendation | H4: Priority (H/M/L) | I4: Best Practice | J4: Maturity (1-5) | K4: Owner | L4: Target Date
A5: 1 | B5: Cost Visibility | C5: Current monthly Snowflake spend (compute / storage / cloud services / data transfer)?
A6: 2 | B6: Cost Visibility | C6: Trend over last 6 months?
A7: 3 | B7: Cost Visibility | C7: Top 10 warehouses by cost? Top 10 users? Top 10 queries?
A8: 4 | B8: Cost Visibility | C8: Is CloudHealth still the primary cost view or is Snowsight/native used?
A9: 5 | B9: Cost Visibility | C9: Tag-based cost allocation implemented (cost center / domain / project)?
A10: 6 | B10: Controls | C10: Resource Monitors set at account and warehouse level with notify + suspend thresholds?
A11: 7 | B11: Controls | C11: Budget alerts and anomaly detection configured?
A12: 8 | B12: Controls | C12: Cloud Services layer cost <10% of daily compute?
A13: 9 | B13: Controls | C13: Idle warehouse detection / auto-suspend tuning?
A14: 10 | B14: Chargeback / Showback | C14: Chargeback or showback model implemented?
A15: 11 | B15: Chargeback / Showback | C15: Cost dashboards published to domain owners?
A16: 12 | B16: Chargeback / Showback | C16: FinOps operating cadence (weekly review, monthly optimization)?
... A19: 15 | B19: Optimization Opportunities | C19: Serverless features (Tasks, Snowpipe, Search Opt) cost reviewed?

Sheet 13_Sharing
A1: 13. Data Sharing & Collaboration
A2: Corewell Snowflake DD&A – capture Current State, Evidence, and Recommendation for each question. Score Maturity 1-5.
A4: Sno | B4: Category | C4: Assessment Question | D4: Current State | E4: Evidence | F4: Risk (H/M/L) | G4: Recommendation | H4: Priority (H/M/L) | I4: Best Practice | J4: Maturity (1-5) | K4: Owner | L4: Target Date
A5: 1 | B5: Internal Sharing | C5: Secure Data Sharing used across accounts / business units?
A6: 2 | B6: Internal Sharing | C6: Reader accounts – any in use? Governance around them?
A7: 3 | B7: External Sharing | C7: Snowflake Marketplace listings – provider or consumer?
A8: 4 | B8: External Sharing | C8: Private Listings for partners / payers / providers?
A9: 5 | B9: External Sharing | C9: Cross-region sharing needs?
A10: 6 | B10: Collaboration | C10: Data Clean Rooms – any use case (payer collaboration, research)?
A11: 7 | B11: Collaboration | C11: External data providers subscribed to (e.g., claims, demographics)?

Sheet 14_DQ
A1: 14. Data Quality
A2: Corewell Snowflake DD&A – capture Current State, Evidence, and Recommendation for each question. Score Maturity 1-5.
A4: Sno | B4: Category | C4: Assessment Question | D4: Current State | E4: Evidence | F4: Risk (H/M/L) | G4: Recommendation | H4: Priority (H/M/L) | I4: Best Practice | J4: Maturity (1-5) | K4: Owner | L4: Target Date
A5: 1 | B5: DQ Framework | C5: Is there a formal DQ framework / policy?
A6: 2 | B6: DQ Framework | C6: DQ dimensions tracked – completeness, accuracy, timeliness, validity, uniqueness, consistency?
A7: 3 | B7: DQ Framework | C7: Tooling – Great Expectations, Soda, Monte Carlo, Anomalo, dbt tests, custom?
A8: 4 | B8: Monitoring | C8: Freshness / SLA monitoring on critical tables?
A9: 5 | B9: Monitoring | C9: Null checks, duplicate checks, referential integrity checks automated?
A10: 6 | B10: Monitoring | C10: Anomaly / drift detection in place?
A11: 7 | B11: Monitoring | C11: DQ incidents tracked, triaged, and reported?
A12: 8 | B12: Lineage & Contracts | C12: End-to-end lineage available (source → transform → BI)?
A13: 9 | B13: Lineage & Contracts | C13: Data contracts between producers and consumers enforced?

Sheet 15_Metadata
A1: 15. Metadata & Catalog
A2: Corewell Snowflake DD&A – capture Current State, Evidence, and Recommendation for each question. Score Maturity 1-5.
A4: Sno | B4: Category | C4: Assessment Question | D4: Current State | E4: Evidence | F4: Risk (H/M/L) | G4: Recommendation | H4: Priority (H/M/L) | I4: Best Practice | J4: Maturity (1-5) | K4: Owner | L4: Target Date
A5: 1 | B5: Catalog Tooling | C5: Data catalog in place – Snowflake Horizon, Alation, Collibra, Purview, DataHub, OpenMetadata?
A6: 2 | B6: Catalog Tooling | C6: Coverage – % of Snowflake objects catalogued?
A7: 3 | B7: Catalog Tooling | C7: Business glossary curated and linked to physical assets?
A8: 4 | B8: Classification & Tagging | C8: Automatic sensitive-data classification enabled (Snowflake classification / third-party)?
A9: 5 | B9: Classification & Tagging | C9: PHI / PII columns tagged consistently?
A10: 6 | B10: Classification & Tagging | C10: Cost / domain / environment tags applied?
A11: 7 | B11: Discovery | C11: Can analysts search and understand datasets self-service?
A12: 8 | B12: Discovery | C12: Certified / gold-standard datasets flagged?

Sheet 16_DevOps
A1: 16. DevOps / CI-CD
A2: Corewell Snowflake DD&A – capture Current State, Evidence, and Recommendation for each question. Score Maturity 1-5.
A4: Sno | B4: Category | C4: Assessment Question | D4: Current State | E4: Evidence | F4: Risk (H/M/L) | G4: Recommendation | H4: Priority (H/M/L) | I4: Best Practice | J4: Maturity (1-5) | K4: Owner | L4: Target Date
A5: 1 | B5: Source Control | C5: All Snowflake DDL, dbt, and pipeline code in Git?
A6: 2 | B6: Source Control | C6: Branching strategy documented (trunk-based / GitFlow)?
A7: 3 | B7: Source Control | C7: Pull request + peer review mandatory?
A8: 4 | B8: CI/CD Pipelines | C8: CI tool – GitHub Actions, Azure DevOps, Jenkins, GitLab CI?
A9: 5 | B9: CI/CD Pipelines | C9: Automated deployment to Dev → Test → Prod?
A10: 6 | B10: CI/CD Pipelines | C10: Schema change management tool – Flyway, Liquibase, schemachange, Terraform-Snowflake, SnowCLI?
A11: 7 | B11: CI/CD Pipelines | C11: dbt Cloud or self-hosted dbt-core scheduled?
A12: 8 | B12: CI/CD Pipelines | C12: Rollback strategy documented?
A13: 9 | B13: Infrastructure as Code | C13: Terraform (Snowflake provider) used for accounts, warehouses, roles, integrations?
A14: 10 | B14: Infrastructure as Code | C14: State file managed (remote backend, locking)?
A15: 11 | B15: Infrastructure as Code | C15: Drift detection in place?

Sheet 17_Monitoring
A1: 17. Monitoring & Observability
A2: Corewell Snowflake DD&A – capture Current State, Evidence, and Recommendation for each question. Score Maturity 1-5.
A4: Sno | B4: Category | C4: Assessment Question | D4: Current State | E4: Evidence | F4: Risk (H/M/L) | G4: Recommendation | H4: Priority (H/M/L) | I4: Best Practice | J4: Maturity (1-5) | K4: Owner | L4: Target Date
A5: 1 | B5: Snowflake-native | C5: ACCOUNT_USAGE / ORGANIZATION_USAGE views leveraged for monitoring?
A6: 2 | B6: Snowflake-native | C6: Snowsight dashboards for cost, performance, users?
A7: 3 | B7: Snowflake-native | C7: Alerts (Snowflake ALERT objects / Serverless Alerts) for cost spikes, long queries, failed tasks?
A8: 4 | B8: Snowflake-native | C8: Event Tables enabled for Snowpark / logging?
A9: 5 | B9: Enterprise Observability | C9: Metrics / logs pushed to Splunk, Datadog, Grafana, Prometheus, CloudWatch, Azure Monitor?
A10: 6 | B10: Enterprise Observability | C10: PagerDuty / ServiceNow integration for incidents?
A11: 7 | B11: Enterprise Observability | C11: Pipeline observability – dbt Cloud / Airflow / Monte Carlo?
A12: 8 | B12: KPIs | C12: Platform SLIs / SLOs defined (uptime, freshness, query latency)?
A13: 9 | B13: KPIs | C13: Weekly / monthly operational review with published KPIs?

Sheet 18_DR
A1: 18. Disaster Recovery & BCP
A2: Corewell Snowflake DD&A – capture Current State, Evidence, and Recommendation for each question. Score Maturity 1-5.
A4: Sno | B4: Category | C4: Assessment Question | D4: Current State | E4: Evidence | F4: Risk (H/M/L) | G4: Recommendation | H4: Priority (H/M/L) | I4: Best Practice | J4: Maturity (1-5) | K4: Owner | L4: Target Date
A5: 1 | B5: Objectives | C5: Documented RTO and RPO per data class / application?
A6: 2 | B6: Objectives | C6: Business Impact Analysis (BIA) done for critical data assets?
A7: 3 | B7: Replication & Failover | C7: Database Replication configured for critical DBs?
A8: 4 | B8: Replication & Failover | C8: Failover Groups / Client Redirect configured?
A9: 5 | B9: Replication & Failover | C9: Cross-region (and if needed cross-cloud) replication?
A10: 6 | B10: Testing | C10: DR drill frequency (annually / semi-annually)?
A11: 7 | B11: Testing | C11: Last DR test outcome documented?
A12: 8 | B12: Testing | C12: Backup strategy for external stages / non-Snowflake assets?
A13: 9 | B13: Testing | C13: Restore-from-clone runbook tested?

Sheet 19_AI
A1: 19. AI / Cortex / ML Readiness
A2: Corewell Snowflake DD&A – capture Current State, Evidence, and Recommendation for each question. Score Maturity 1-5.
A4: Sno | B4: Category | C4: Assessment Question | D4: Current State | E4: Evidence | F4: Risk (H/M/L) | G4: Recommendation | H4: Priority (H/M/L) | I4: Best Practice | J4: Maturity (1-5) | K4: Owner | L4: Target Date
A5: 1 | B5: Cortex | C5: Cortex LLM Functions in use (COMPLETE, SUMMARIZE, TRANSLATE, SENTIMENT, EXTRACT_ANSWER)?
A6: 2 | B6: Cortex | C6: Cortex Search / Cortex Analyst evaluated for internal Q&A?
A7: 3 | B7: Cortex | C7: Document AI evaluated for clinical / claims document extraction?
A8: 4 | B8: ML Platform | C8: Snowpark ML / Model Registry in use?
A9: 5 | B9: ML Platform | C9: Feature Store approach?
A10: 6 | B10: ML Platform | C10: Vector data type + embeddings – use cases identified?
A11: 7 | B11: Integrations | C11: External model integration – AWS Bedrock, Azure OpenAI, Vertex AI?
A12: 8 | B12: Integrations | C12: Governance for LLM prompts / PHI exposure (data leaves boundary)?
A13: 9 | B13: Integrations | C13: Native Apps – provider or consumer?
A14: 10 | B14: Integrations | C14: Semantic layer / RAG architecture defined?
A15: 11 | B15: Enablement | C15: Data science personas onboarded – tools, environments, budget?
A16: 12 | B16: Enablement | C16: Responsible AI / model risk framework applied?

Sheet 20_Compliance
A1: 20. Compliance & Audit (HIPAA / HITRUST)
A2: Corewell Snowflake DD&A – capture Current State, Evidence, and Recommendation for each question. Score Maturity 1-5.
A4: Sno | B4: Category | C4: Assessment Question | D4: Current State | E4: Evidence | F4: Risk (H/M/L) | G4: Recommendation | H4: Priority (H/M/L) | I4: Best Practice | J4: Maturity (1-5) | K4: Owner | L4: Target Date
A5: 1 | B5: Regulatory Scope | C5: Applicable frameworks – HIPAA, HITRUST, SOC 2, ISO 27001, NIST 800-53, PCI DSS, GDPR, CCPA?
A6: 2 | B6: Regulatory Scope | C6: Snowflake edition – HIPAA/HITRUST enabled (Business Critical or higher)?
A7: 3 | B7: Regulatory Scope | C7: BAA in place with Snowflake and all sub-processors?
A8: 4 | B8: PHI/PII Controls | C8: PHI/PII inventory maintained – which tables, columns?
A9: 5 | B9: PHI/PII Controls | C9: Masking / row policies validated by an internal audit?
A10: 6 | B10: PHI/PII Controls | C10: De-identification (Safe Harbor / Expert Determination) applied where required?
A11: 7 | B11: PHI/PII Controls | C11: ClearData (or equivalent) validation of managed services still active?
A12: 8 | B12: Audit & Logging | C12: ACCESS_HISTORY, LOGIN_HISTORY, QUERY_HISTORY retained per retention policy?
A13: 9 | B13: Audit & Logging | C13: Object access / column access audit integrated with SIEM?
A14: 10 | B14: Audit & Logging | C14: Privileged action review cadence?
A15: 11 | B15: Audit & Logging | C15: Legal Hold process defined?
A16: 12 | B16: Third-Party Risk | C16: TPRM review completed for all integrated tools (Fivetran, dbt Cloud, BI, ML)?

Sheet 21_Ops
A1: 21. Operations & SLA
A2: Corewell Snowflake DD&A – capture Current State, Evidence, and Recommendation for each question. Score Maturity 1-5.
A4: Sno | B4: Category | C4: Assessment Question | D4: Current State | E4: Evidence | F4: Risk (H/M/L) | G4: Recommendation | H4: Priority (H/M/L) | I4: Best Practice | J4: Maturity (1-5) | K4: Owner | L4: Target Date
A5: 1 | B5: Service Management | C5: Documented SLA / SLOs for the platform?
A6: 2 | B6: Service Management | C6: Incident management process (P1-P4) and runbooks?
A7: 3 | B7: Service Management | C7: Change management – CAB / approvals for prod changes?
A8: 4 | B8: Service Management | C8: Release calendar and freeze windows?
A9: 5 | B9: Capacity & Planning | C9: Capacity planning cadence (compute, storage, licenses)?
A10: 6 | B10: Capacity & Planning | C10: Onboarding / offboarding runbooks for users, apps, domains?
A11: 7 | B11: Continuous Improvement | C11: Post-incident reviews / blameless post-mortems?
A12: 8 | B12: Continuous Improvement | C12: Platform Health Score published?
A13: 9 | B13: Continuous Improvement | C13: Automation coverage vs manual toil measured?
A14: 10 | B14: Reporting Tool Rationalization | C14: Tableau, PowerBI, SAS, MS Access – which is strategic? Which is being retired?
A15: 11 | B15: Reporting Tool Rationalization | C15: Semantic consistency across BI tools?
A16: 12 | B16: Reporting Tool Rationalization | C16: License optimization opportunities?

Sheet 22_Roadmap
A1: 22. Roadmap & Recommendations
A2: Corewell Snowflake DD&A – capture Current State, Evidence, and Recommendation for each question. Score Maturity 1-5.
A4: Sno | B4: Category | C4: Assessment Question | D4: Current State | E4: Evidence | F4: Risk (H/M/L) | G4: Recommendation | H4: Priority (H/M/L) | I4: Best Practice | J4: Maturity (1-5) | K4: Owner | L4: Target Date
A5: 1 | B5: Quick Wins (0-30 days) | C5: Enable / tune Resource Monitors and cost alerts.
A6: 2 | B6: Quick Wins (0-30 days) | C6: Right-size top 5 most expensive warehouses.
A7: 3 | B7: Quick Wins (0-30 days) | C7: Enforce MFA + SSO on any remaining local users.
A8: 4 | B8: Quick Wins (0-30 days) | C8: Enable ACCESS_HISTORY / retention config review.
A9: 5 | B9: Quick Wins (0-30 days) | C9: Publish a Snowsight cost + performance dashboard.
A10: 6 | B10: 30-60 Days | C10: Formalize RBAC (functional + access roles) and future grants.
A11: 7 | B11: 30-60 Days | C11: Deploy tagging strategy (cost center, sensitivity, domain).
A12: 8 | B12: 30-60 Days | C12: Stand up dbt + Git + CI/CD baseline (if not already).
A13: 9 | B13: 30-60 Days | C13: Baseline DQ tests on top 20 critical tables.
A14: 10 | B14: 30-60 Days | C14: Draft PHI masking / row policy standards and pilot.
A15: 11 | B15: 60-90 Days | C15: PrivateLink rollout across environments.
A16: 12 | B16: 60-90 Days | C16: Data catalog rollout (Horizon or existing) with tag propagation.
... A24: 20 | B24: 3-12 Months (Strategic) | C24: AI / ML platform (Snowpark ML + Cortex + Feature Store) production-ready.

Sheet Executive Summary
A1: Executive Summary – Maturity Scorecard
A2: Average maturity per domain rolls up from each section tab (column J - Maturity 1-5).
A4: Sno | B4: Domain | C4: Avg Maturity (1-5) | D4: # Questions Scored | E4: Risk (H/M/L) | F4: Top Recommendation
A5: 1 | B5: 1. Organization & Governance | C5: =IFERROR(AVERAGE('1_Governance'!J5:J200),"-") -> - | D5: =COUNT('1_Governance'!J5:J200) -> 0
A6: 2 | B6: 2. Snowflake Account Architecture | C6: =IFERROR(AVERAGE('2_AccountArch'!J5:J200),"-") -> - | D6: =COUNT('2_AccountArch'!J5:J200) -> 0
A7: 3 | B7: 3. Security & Identity | C7: =IFERROR(AVERAGE('3_Security'!J5:J200),"-") -> - | D7: =COUNT('3_Security'!J5:J200) -> 0
A8: 4 | B8: 4. Networking | C8: =IFERROR(AVERAGE('4_Networking'!J5:J200),"-") -> - | D8: =COUNT('4_Networking'!J5:J200) -> 0
A9: 5 | B9: 5. Data Architecture | C9: =IFERROR(AVERAGE('5_DataArch'!J5:J200),"-") -> - | D9: =COUNT('5_DataArch'!J5:J200) -> 0
A10: 6 | B10: 6. Data Ingestion | C10: =IFERROR(AVERAGE('6_Ingestion'!J5:J200),"-") -> - | D10: =COUNT('6_Ingestion'!J5:J200) -> 0
A11: 7 | B11: 7. Data Transformation | C11: =IFERROR(AVERAGE('7_Transform'!J5:J200),"-") -> - | D11: =COUNT('7_Transform'!J5:J200) -> 0
A12: 8 | B12: 8. Data Modeling | C12: =IFERROR(AVERAGE('8_Modeling'!J5:J200),"-") -> - | D12: =COUNT('8_Modeling'!J5:J200) -> 0
A13: 9 | B13: 9. Compute & Warehouses | C13: =IFERROR(AVERAGE('9_Compute'!J5:J200),"-") -> - | D13: =COUNT('9_Compute'!J5:J200) -> 0
A14: 10 | B14: 10. Storage & Data Lifecycle | C14: =IFERROR(AVERAGE('10_Storage'!J5:J200),"-") -> - | D14: =COUNT('10_Storage'!J5:J200) -> 0
A15: 11 | B15: 11. Performance Optimization | C15: =IFERROR(AVERAGE('11_Performance'!J5:J200),"-") -> - | D15: =COUNT('11_Performance'!J5:J200) -> 0
A16: 12 | B16: 12. Cost Optimization (FinOps) | C16: =IFERROR(AVERAGE('12_FinOps'!J5:J200),"-") -> - | D16: =COUNT('12_FinOps'!J5:J200) -> 0
A17: 13 | B17: 13. Data Sharing & Collaboration | C17: =IFERROR(AVERAGE('13_Sharing'!J5:J200),"-") -> - | D17: =COUNT('13_Sharing'!J5:J200) -> 0
A18: 14 | B18: 14. Data Quality | C18: =IFERROR(AVERAGE('14_DQ'!J5:J200),"-") -> - | D18: =COUNT('14_DQ'!J5:J200) -> 0
A19: 15 | B19: 15. Metadata & Catalog | C19: =IFERROR(AVERAGE('15_Metadata'!J5:J200),"-") -> - | D19: =COUNT('15_Metadata'!J5:J200) -> 0
A20: 16 | B20: 16. DevOps / CI-CD | C20: =IFERROR(AVERAGE('16_DevOps'!J5:J200),"-") -> - | D20: =COUNT('16_DevOps'!J5:J200) -> 0
A21: 17 | B21: 17. Monitoring & Observability | C21: =IFERROR(AVERAGE('17_Monitoring'!J5:J200),"-") -> - | D21: =COUNT('17_Monitoring'!J5:J200) -> 0
A22: 18 | B22: 18. Disaster Recovery & BCP | C22: =IFERROR(AVERAGE('18_DR'!J5:J200),"-") -> - | D22: =COUNT('18_DR'!J5:J200) -> 0
A23: 19 | B23: 19. AI / Cortex / ML Readiness | C23: =IFERROR(AVERAGE('19_AI'!J5:J200),"-") -> - | D23: =COUNT('19_AI'!J5:J200) -> 0
A24: 20 | B24: 20. Compliance & Audit (HIPAA / HITRUST) | C24: =IFERROR(AVERAGE('20_Compliance'!J5:J200),"-") -> - | D24: =COUNT('20_Compliance'!J5:J200) -> 0
A25: 21 | B25: 21. Operations & SLA | C25: =IFERROR(AVERAGE('21_Ops'!J5:J200),"-") -> - | D25: =COUNT('21_Ops'!J5:J200) -> 0
A26: 22 | B26: 22. Roadmap & Recommendations | C26: =IFERROR(AVERAGE('22_Roadmap'!J5:J200),"-") -> - | D26: =COUNT('22_Roadmap'!J5:J200) -> 0
B27: OVERALL PLATFORM MATURITY | C27: =IFERROR(AVERAGE(C5:C26),"-") -> -

Sheet Tool Chain
A1: Current Tool Chain & Rationalization
A3: Sno | B3: Category | C3: Tool | D3: Use Case | E3: Current State | F3: Replace with Cloud-Native? | G3: Long-term Plan | H3: Decision | I3: Owner
A4: 1 | B4: 3rd Party | C4: CloudHealth | D4: Cost visibility / reporting
A5: 2 | B5: 3rd Party | C5: ClearData | D5: HIPAA compliance validation for managed services
A6: 3 | B6: Azure | C6: Azure AD | D6: Identity / SSO / SCIM source
A7: 4 | B7: Microsoft | C7: MS SQL Server | D7: OLTP / RDBMS source
A8: 5 | B8: IBM | C8: IBM DB2 | D8: Structured data warehouse (legacy)
A9: 6 | B9: IBM | C9: IBM IaaS DW | D9: Data warehouse platform – compute/storage (legacy)
A10: 7 | B10: Reporting | C10: Tableau | D10: Enterprise BI
A11: 8 | B11: Reporting | C11: MS Access | D11: Desktop reporting / departmental
A12: 9 | B12: Reporting | C12: MS PowerBI | D12: Enterprise BI
A13: 10 | B13: Reporting | C13: SAS | D13: Advanced analytics / statistical reporting
A14: 11 | B14: Integration | C14: SFTP | D14: Flat file exchange with external parties
A15: 12 | B15: Database | C15: MongoDB | D15: Document / semi-structured store
